mdas_python_sdk/README.md
mdas_python_sdk/__init__.py
mdas_python_sdk/auth.py
mdas_python_sdk/client.py
mdas_python_sdk/config.py
mdas_python_sdk/setup.py
mdas_python_sdk/core/__init__.py
mdas_python_sdk/core/http_client.py
mdas_python_sdk/helpers/logger.py
mdas_python_sdk/models/__init__.py
mdas_python_sdk/models/quote.py
mdas_python_sdk/services/__init__.py
mdas_python_sdk/services/account_service.py
mdas_python_sdk/services/quote_service.py
mdas_python_sdk-0.1.3.dist-info/METADATA
mdas_python_sdk-0.1.3.dist-info/WHEEL
mdas_python_sdk-0.1.3.dist-info/RECORD
