Metadata-Version: 2.4
Name: mdas-python-sdk
Version: 0.1.3
Summary: Python SDK for MDAS API.
Project-URL: Source, https://github.com/OrbisSystems/mdas-python-sdk
Author-email: Roxanne Resuello <roxanne.resuello@orbisfn.com>
License: MIT
Classifier: License :: OSI Approved :: MIT License
Classifier: Operating System :: OS Independent
Classifier: Programming Language :: Python :: 3
Requires-Python: >=3.7
Requires-Dist: colorlog>=6.0.0
Requires-Dist: requests>=2.32.0
